imagecompression5/__init__.py
imagecompression5/helpers.py
imagecompression5/image_compression.py
imagecompression5/reis_algorithm.py
imagecompression5-0.1.2.dist-info/LICENSE.txt
imagecompression5-0.1.2.dist-info/METADATA
imagecompression5-0.1.2.dist-info/WHEEL
imagecompression5-0.1.2.dist-info/top_level.txt
imagecompression5-0.1.2.dist-info/RECORD
