Metadata-Version: 2.1
Name: imagecompression5
Version: 0.1.2
Summary: Image compression using REIS algorithms
Author: Katie Wen Ling Kuo
Author-email: katie20030705@gmail.com
License: MIT
Classifier: License :: OSI Approved :: MIT License
Classifier: Programming Language :: Python :: 3
Requires-Python: >=3.6
License-File: LICENSE.txt
